Metadata-Version: 1.0
Name: MyNewLib
Version: 1.1.1
Summary: My first Python library
Home-page: UNKNOWN
Author: Hamed
Author-email: UNKNOWN
License: UNKNOWN
Platform: UNKNOWN
